shanten_tools-0.1.8.dist-info/METADATA
shanten_tools-0.1.8.dist-info/WHEEL
shanten_tools/__init__.py
shanten_tools/shanten_tools.pypy39-pp73-x86_64-linux-gnu.so
shanten_tools-0.1.8.dist-info/RECORD
